{
  "name": "Adeline Alvarez",
  "age": 44,
  "address": {
    "street": "Ceiru Path",
    "city": "Noneda",
    "state": "DC",
    "zip": "14166"
  },
  "contact": {
    "phone": "(857) 324-7460",
    "servicePhone": "800871767"
  },
  "birthday": "1969-04-03T18:20:38.653Z",
  "ip": "116.154.98.145",
  "foo": "bar",
  "profile": {
    "about": "Gibko wadubam miju ziohune dubwadob kuz anuikwa hegcugid mekih ribcohiv nahidmaw ohda zofolo. Umza mu kan hoihu cujijutin zosmapo pedecjit ehsuoni vac jashutga fofed walahon gun cifgo anabe ekifibuk ho comib. Ordu pumgab uborubab da wotgocza sagrufge jar woztodpuk bozohu conezzoc coajiwaf zemdevob satu. Otoce roh uwafoc ittu sugka apose bamoga risuaz uni pusiczog guc tohan ug. Lu can mesdeswim duf wa macmiwud ige pufcaz lokepu geeri los es ha kiv ke dutalrum huhehwe liuri. Molugnog votsizir hezusbo evanucab ofet ewa kujol intip kutwuw if rub romgehlu va.",
    "bio": "Dekarme tablam ho fid wusbit duur busa benopwe iboan viapaag pagpul zursuum cidag. Ra dovpaile bilo ruziwcem hefo jettas lujbe omip piclafub ku wiunuuf lajepcaz ebdocace uvgi zef batof. Guku vedlosa tewafazoh buscinup holiwor lackowi je ibo hu tupom pobonipu cuzfive ma rikwaewi bic dieru deffe vu. Buet giohu ivaceco ven foefede cobpugeh mahel dujuuj ni gub rek zocu huw ko secapzum duroli onigeola."
  },
  "apiKey": "e9791ff61220b71ea7280cb337d522af3d75b0e905ea6b21c857c86e1b46f5b6",
  "currency": {
    "code": "EUR",
    "name": "Euro Member Countries"
  }
}