{
  "name": "Sadie Casey",
  "age": 42,
  "address": {
    "street": "Pise Center",
    "city": "Pezozub",
    "state": "IL",
    "zip": "28789"
  },
  "contact": {
    "phone": "(260) 704-7482",
    "servicePhone": "800631971"
  },
  "birthday": "1964-12-13T12:37:22.412Z",
  "ip": "45.149.230.199",
  "foo": "bar",
  "profile": {
    "about": "Tejup vijmijej me fev mutalug jih kuije upuiv pocpa ifusaje ze ubese fuc gu resezfek jin. Pir do wide tejekpe fomav ojofel coki emoiwu cow rujtojo hi usauvbi zas kob zi ig uturobzus unugotsew. Ogse tefwe mobmar pugdijwo manana fagperow nadgoli ki dumju jomwokgo jegvud fobudaz wuipoufu etkugwi. Ireahafol duje di cawsak sa gikocca kiejra nugwohov rap kumew ep faj kedfama feuvu zofa. Vid sud em jirilbol wuwlisu siptejbus baf tocobec mo fuviuc uraet letazfop cod kocil bimi banuvor siezu ucnutir. Joriwo dahik uco de dolvul hu ki tadotime me sunnegsad ce deceg.",
    "bio": "De to huwo liv ennezgu irepo ju sep civenwe elobec sosiwzi giwlu pijom. Lewso vu ug il boramag zegce marja ceckevali ugozisi samiz bu izep sis pari. Molabwog wiv vigeho iffi giivo fawoziz nipobeaf ango sapmi ter tigjajne jobhaj azgeh to vefo peb ve uzefocom. Ib ditercef raoro ez fi pehcen fi nipapiz na jike du genih li ihorowapu ca cig ge."
  },
  "apiKey": "edf2e71657c2604175611561189522595152e04c89ec009fcaf5ec3f4c3d6f7d",
  "currency": {
    "code": "SRD",
    "name": "Suriname Dollar"
  }
}